pressoir/__init__.py
pressoir/__main__.py
pressoir/additionals.py
pressoir/cli.py
pressoir/corpus.py
pressoir/generator.py
pressoir/indexes.py
pressoir/models.py
pressoir/project.toml
pressoir/search.py
pressoir/sidenotes.py
pressoir/statics.py
pressoir/utils.py
pressoir/docs/pressoir/book.toml
pressoir/docs/pressoir/static/css/custom.css
pressoir/docs/pressoir/static/css/fonts.css
pressoir/docs/pressoir/static/css/vars.css
pressoir/docs/pressoir/static/fonts/averialibre-bold.woff2
pressoir/docs/pressoir/static/fonts/averialibre-bolditalic.woff2
pressoir/docs/pressoir/static/fonts/averiaseriflibre-light.woff2
pressoir/docs/pressoir/static/img/pressoir-logo.png
pressoir/docs/pressoir/static/svg/minus.svg
pressoir/docs/pressoir/static/svg/parcours-numeriques.png
pressoir/docs/pressoir/static/svg/personnalite.svg
pressoir/docs/pressoir/static/svg/plus.svg
pressoir/docs/pressoir/static/svg/pum-logo-couleur.svg
pressoir/docs/pressoir/static/svg/pum-logo-noir.svg
pressoir/docs/pressoir/static/svg/quote.svg
pressoir/docs/textes/bibliographie/bibliographie.bib
pressoir/docs/textes/bibliographie/bibliographie.md
pressoir/docs/textes/bibliographie/bibliographie.yaml
pressoir/docs/textes/chapitre1/additionnels.md
pressoir/docs/textes/chapitre1/chapitre1.md
pressoir/docs/textes/chapitre1/chapitre1.yaml
pressoir/docs/textes/chapitre2/additionnels.md
pressoir/docs/textes/chapitre2/chapitre2.md
pressoir/docs/textes/chapitre2/chapitre2.yaml
pressoir/docs/textes/chapitre3/additionnels.md
pressoir/docs/textes/chapitre3/chapitre3.md
pressoir/docs/textes/chapitre3/chapitre3.yaml
pressoir/docs/textes/chapitre4/additionnels.md
pressoir/docs/textes/chapitre4/chapitre4.md
pressoir/docs/textes/chapitre4/chapitre4.yaml
pressoir/docs/textes/dev/additionnels.md
pressoir/docs/textes/dev/dev.bib
pressoir/docs/textes/dev/dev.md
pressoir/docs/textes/dev/dev.yaml
pressoir/docs/textes/faq/additionnels.md
pressoir/docs/textes/faq/faq.bib
pressoir/docs/textes/faq/faq.md
pressoir-4.9.3.dist-info/METADATA
pressoir-4.9.3.dist-info/WHEEL
pressoir-4.9.3.dist-info/entry_points.txt
pressoir-4.9.3.dist-info/licenses/LICENSE
pressoir-4.9.3.dist-info/RECORD
