Metadata-Version: 2.4
Name: pressoir
Version: 4.9.3
Summary: A Static Book Generator.
Project-URL: Homepage, https://pressoir.org
Project-URL: Source, https://gitlab.huma-num.fr/ecrinum/pressoir
Project-URL: Documentation, https://pressoir.org
Project-URL: Issues, https://gitlab.huma-num.fr/ecrinum/pressoir/-/issues
Project-URL: Changelog, https://gitlab.huma-num.fr/ecrinum/pressoir/-/blob/main/CHANGELOG.md?#changelog
License:                     GNU AFFERO GENERAL PUBLIC LICENSE
License-File: LICENSE
Keywords: book,generator,pandoc,publishing
Classifier: Development Status :: 5 - Production/Stable
Classifier: Intended Audience :: Education
Classifier: Intended Audience :: Information Technology
Classifier: Intended Audience :: Science/Research
Classifier: License :: OSI Approved :: GNU Affero General Public License v3
Classifier: Programming Language :: Python :: 3
Classifier: Programming Language :: Python :: 3.8
Classifier: Programming Language :: Python :: 3.9
Classifier: Programming Language :: Python :: 3.10
Classifier: Programming Language :: Python :: 3.11
Classifier: Programming Language :: Python :: 3.12
Classifier: Topic :: Documentation
Classifier: Topic :: Software Development :: Build Tools
Classifier: Topic :: Text Processing :: Markup :: Markdown
Requires-Python: >=3.8
Requires-Dist: dataclass-wizard
Requires-Dist: httpx
Requires-Dist: jinja2
Requires-Dist: minicli
Requires-Dist: mistune
Requires-Dist: progressist
Requires-Dist: pypandoc
Requires-Dist: python-slugify
Requires-Dist: pyyaml
Requires-Dist: selectolax
Requires-Dist: tomli>=1.1.0; python_version < '3.11'
Requires-Dist: unidecode
Provides-Extra: dev
Requires-Dist: black; extra == 'dev'
Requires-Dist: cogapp; extra == 'dev'
Requires-Dist: hatch; extra == 'dev'
Requires-Dist: isort; extra == 'dev'
Requires-Dist: pytest; extra == 'dev'
Requires-Dist: ruff; extra == 'dev'
